odoo/addons/l10n_br_purchase_request/README.rst
odoo/addons/l10n_br_purchase_request/__init__.py
odoo/addons/l10n_br_purchase_request/__manifest__.py
odoo/addons/l10n_br_purchase_request/i18n/l10n_br_purchase_request.pot
odoo/addons/l10n_br_purchase_request/i18n/pt_BR.po
odoo/addons/l10n_br_purchase_request/readme/CONFIGURE.rst
odoo/addons/l10n_br_purchase_request/readme/CONTRIBUTORS.rst
odoo/addons/l10n_br_purchase_request/readme/CREDITS.rst
odoo/addons/l10n_br_purchase_request/readme/DESCRIPTION.rst
odoo/addons/l10n_br_purchase_request/readme/INSTALL.rst
odoo/addons/l10n_br_purchase_request/readme/USAGE.rst
odoo/addons/l10n_br_purchase_request/static/description/icon.png
odoo/addons/l10n_br_purchase_request/static/description/index.html
odoo/addons/l10n_br_purchase_request/tests/__init__.py
odoo/addons/l10n_br_purchase_request/tests/test_l10n_br_purchase_request.py
odoo/addons/l10n_br_purchase_request/wizards/__init__.py
odoo/addons/l10n_br_purchase_request/wizards/purchase_request_line_make_purchase_order.py
odoo14_addon_l10n_br_purchase_request-14.0.1.0.4.dist-info/METADATA
odoo14_addon_l10n_br_purchase_request-14.0.1.0.4.dist-info/WHEEL
odoo14_addon_l10n_br_purchase_request-14.0.1.0.4.dist-info/top_level.txt
odoo14_addon_l10n_br_purchase_request-14.0.1.0.4.dist-info/RECORD
